Metadata-Version: 2.1
Name: oms-magento
Version: 1.0.0
Summary: Integration courier Magento
Home-page: https://gitlab.com/linets/ecommerce/oms/integrations/oms-magento/
Author: Linets team
Author-email: avelasqueza@linets.cl
License: MIT
Platform: UNKNOWN
Requires-Python: >=3.7
